{
  "notes": [
    {
      "text": "steak",
      "checked": false,
      "priority": "Low",
      "id": 1
    },
    {
      "text": "veggies",
      "checked": true,
      "priority": "Low",
      "id": 2
    },
    {
      "text": "bbq sauce",
      "checked": false,
      "priority": "Low",
      "id": 3
    },
    {
      "text": "salad",
      "checked": false,
      "priority": "Low",
      "id": 4
    },
    {
      "text": "balsamiq",
      "checked": false,
      "priority": "Low",
      "id": 5
    },
    {
      "text": "beer",
      "checked": false,
      "priority": "Low",
      "id": 6
    },
    {
      "text": "burger",
      "checked": false,
      "priority": "Low",
      "id": 7
    },
    {
      "text": "add",
      "checked": false,
      "priority": "Low",
      "id": 8
    },
    {
      "text": "add",
      "checked": false,
      "priority": "Low",
      "id": 9
    },
    {
      "text": "add",
      "checked": false,
      "priority": "Low",
      "id": 10
    },
    {
      "text": "add",
      "checked": false,
      "priority": "Low",
      "id": 11
    },
    {
      "text": "add",
      "checked": false,
      "priority": "Low",
      "id": 12
    },
    {
      "text": "add",
      "checked": false,
      "priority": "Low",
      "id": 13
    },
    {
      "text": "add",
      "checked": false,
      "priority": "Low",
      "id": 14
    },
    {
      "text": "add",
      "checked": false,
      "priority": "Low",
      "id": 15
    },
    {
      "text": "add",
      "checked": false,
      "priority": "Low",
      "id": 16
    },
    {
      "text": "add",
      "checked": false,
      "priority": "Low",
      "id": 17
    },
    {
      "text": "sef",
      "checked": false,
      "priority": "Low",
      "id": 18
    },
    {
      "text": "add",
      "checked": false,
      "priority": "Low",
      "id": 19
    },
    {
      "text": "add",
      "checked": false,
      "priority": "Low",
      "id": 20
    },
    {
      "text": "add",
      "checked": false,
      "priority": "Low",
      "id": 21
    },
    {
      "text": "type",
      "checked": false,
      "priority": "Low",
      "id": 22
    },
    {
      "text": "add",
      "checked": false,
      "priority": "Low",
      "id": 23
    },
    {
      "text": "add",
      "checked": false,
      "priority": "Low",
      "id": 24
    }
  ]
}